test/__init__.py
test/conftest.py
test/t_knots.py
test/test_Wanda_homfly_pdvirtual.py
test/test_a_mac.py
test/test_draw_tangle.py
test/test_gln.py
test/test_homfly_polynomials.py
test/test_import_files.py
test/test_knots.py
test/test_lassos.py
test/test_links_real.py
test/test_matrices.py
test/test_polygongen.py
test/test_polynomials.py
test/test_spatial_graph.py
test/test_speedup.py
test/data/__init__.py
test/data/unknown_dictionary.py
topoly/__init__.py
topoly/codes.py
topoly/convert.py
topoly/graph.py
topoly/invariants.py
topoly/knotcon.py
topoly/lasso.py
topoly/manipulation.py
topoly/params.py
topoly/plotting.py
topoly/polvalues.py
topoly/polygongen.py
topoly/polynomial.py
topoly/setup.py
topoly/tangle_drawing.py
topoly/topoly_gln.cpython-311-darwin.so
topoly/topoly_homfly.cpython-311-darwin.so
topoly/topoly_knot.cpython-311-darwin.so
topoly/topoly_lmpoly.cpython-311-darwin.so
topoly/topoly_preprocess.cpython-311-darwin.so
topoly/topoly_surfaces.cpython-311-darwin.so
topoly-1.1.0.data/data/bin/gln
topoly-1.1.0.data/data/bin/homflylink
topoly-1.1.0.data/data/bin/knotnet
topoly-1.1.0.data/data/bin/ncuclinks
topoly-1.1.0.data/data/bin/surfacesmytraj
topoly-1.1.0.data/data/include/libgln.h
topoly-1.1.0.data/data/include/libhomfly.h
topoly-1.1.0.data/data/include/libknot.h
topoly-1.1.0.data/data/include/libpreprocess.h
topoly-1.1.0.data/data/include/libsurfaces.h
topoly-1.1.0.data/data/include/lmpolyWN.h
topoly-1.1.0.data/data/lib/libglnfinder.dylib
topoly-1.1.0.data/data/lib/libhomfly.dylib
topoly-1.1.0.data/data/lib/libknotfinder.dylib
topoly-1.1.0.data/data/lib/liblmpoly.dylib
topoly-1.1.0.data/data/lib/libpreprocess.dylib
topoly-1.1.0.data/data/lib/libsurfaces.dylib
topoly-1.1.0.data/data/lib/python3/dist-packages/topoly/topoly_gln.cpython-311-darwin.so
topoly-1.1.0.data/data/lib/python3/dist-packages/topoly/topoly_homfly.cpython-311-darwin.so
topoly-1.1.0.data/data/lib/python3/dist-packages/topoly/topoly_knot.cpython-311-darwin.so
topoly-1.1.0.data/data/lib/python3/dist-packages/topoly-1.1.0.egg-info/.keep
topoly-1.1.0.data/data/lib/python3/dist-packages/topoly-1.1.0.egg-info/PKG-INFO
topoly-1.1.0.data/data/lib/python3/dist-packages/topoly-1.1.0.egg-info/SOURCES.txt
topoly-1.1.0.data/data/lib/python3/dist-packages/topoly-1.1.0.egg-info/dependency_links.txt
topoly-1.1.0.data/data/lib/python3/dist-packages/topoly-1.1.0.egg-info/not-zip-safe
topoly-1.1.0.data/data/lib/python3/dist-packages/topoly-1.1.0.egg-info/requires.txt
topoly-1.1.0.data/data/lib/python3/dist-packages/topoly-1.1.0.egg-info/top_level.txt
topoly-1.1.0.dist-info/.keep
topoly-1.1.0.dist-info/LICENSE
topoly-1.1.0.dist-info/METADATA
topoly-1.1.0.dist-info/WHEEL
topoly-1.1.0.dist-info/top_level.txt
topoly-1.1.0.dist-info/RECORD
