Metadata-Version: 2.4
Name: topoly
Version: 1.1.0
Summary: This package provides a set of tools for modeling protein knots, lassos and other.
Home-page: https://topoly.cent.uw.edu.pl/
Author: INTERDISCIPLINARY LABORATORY of BIOLOGICAL SYSTEMS MODELLING, University of Warsaw, Warsaw, Poland
Author-email: jsulkowska@cent.uw.edu.pl
Classifier: Programming Language :: Python :: 3
Classifier: Programming Language :: Python :: 3.6
Classifier: Programming Language :: Python :: 3.7
Classifier: Programming Language :: Python :: 3.8
Classifier: Programming Language :: Python :: 3.9
Classifier: Programming Language :: Python :: 3.10
Classifier: Programming Language :: Python :: 3.11
Classifier: Programming Language :: Python :: 3.12
Classifier: Programming Language :: Python :: 3.13
Classifier: License :: Free for non-commercial use
Classifier: Operating System :: Unix
Classifier: Operating System :: POSIX :: Linux
Classifier: Operating System :: MacOS :: MacOS X
Classifier: Operating System :: Microsoft :: Windows
Classifier: Intended Audience :: Science/Research
Classifier: Intended Audience :: Healthcare Industry
Classifier: Topic :: Scientific/Engineering :: Bio-Informatics
Classifier: Topic :: Scientific/Engineering :: Mathematics
Classifier: Topic :: Scientific/Engineering :: Chemistry
Classifier: Topic :: Scientific/Engineering :: Physics
Requires-Python: >=3.6.0
License-File: LICENSE
Requires-Dist: Pillow
Requires-Dist: matplotlib>=3.0.0
Requires-Dist: numpy
Requires-Dist: argparse>=1.4
Requires-Dist: scipy
Requires-Dist: biopython>1.60
Dynamic: author
Dynamic: author-email
Dynamic: classifier
Dynamic: description
Dynamic: description-content-type
Dynamic: home-page
Dynamic: license-file
Dynamic: requires-dist
Dynamic: requires-python
Dynamic: summary
